mclab-0.0.1.dist-info/licenses/LICENSE
mclab_func/__init__.py
mclab_func/_modidx.py
mclab_func/core.py
mclab_func/mclab_footprint_compute.py
mclab-0.0.1.dist-info/METADATA
mclab-0.0.1.dist-info/WHEEL
mclab-0.0.1.dist-info/entry_points.txt
mclab-0.0.1.dist-info/top_level.txt
mclab-0.0.1.dist-info/RECORD
